stonerplots/__init__.py
stonerplots/colours.py
stonerplots/counter.py
stonerplots/format.py
stonerplots/util.py
stonerplots/context/__init__.py
stonerplots/context/base.py
stonerplots/context/double_y.py
stonerplots/context/inset_plot.py
stonerplots/context/multiple_plot.py
stonerplots/context/noframe.py
stonerplots/context/save_figure.py
stonerplots/styles/notebook.mplstyle
stonerplots/styles/poster.mplstyle
stonerplots/styles/presentation.mplstyle
stonerplots/styles/scatter.mplstyle
stonerplots/styles/stoner.mplstyle
stonerplots/styles/thesis.mplstyle
stonerplots/styles/color/bright.mplstyle
stonerplots/styles/color/high-contrast.mplstyle
stonerplots/styles/color/high-vis.mplstyle
stonerplots/styles/color/light.mplstyle
stonerplots/styles/color/muted.mplstyle
stonerplots/styles/color/retro.mplstyle
stonerplots/styles/color/std-colours.mplstyle
stonerplots/styles/color/stoner_dark.mplstyle
stonerplots/styles/color/vibrant.mplstyle
stonerplots/styles/journals/aaas-science.mplstyle
stonerplots/styles/journals/aip.mplstyle
stonerplots/styles/journals/aps.mplstyle
stonerplots/styles/journals/ieee.mplstyle
stonerplots/styles/journals/iop.mplstyle
stonerplots/styles/journals/nature.mplstyle
stonerplots/styles/misc/grid.mplstyle
stonerplots/styles/misc/pgf.mplstyle
stonerplots/styles/modifiers/aip2.mplstyle
stonerplots/styles/modifiers/aps1.5.mplstyle
stonerplots/styles/modifiers/aps2.mplstyle
stonerplots/styles/modifiers/hi-res.mplstyle
stonerplots/styles/modifiers/latex-sans.mplstyle
stonerplots/styles/modifiers/latex.mplstyle
stonerplots/styles/modifiers/med-res.mplstyle
stonerplots/styles/modifiers/no-latex.mplstyle
stonerplots/styles/modifiers/presentation_dark.mplstyle
stonerplots/styles/modifiers/presentation_sm.mplstyle
stonerplots/styles/modifiers/sans.mplstyle
stonerplots/styles/modifiers/science-2col.mplstyle
stonerplots/styles/modifiers/science-3col.mplstyle
stonerplots/styles/modifiers/thesis-sm.mplstyle
stonerplots-1.9.0.dist-info/licenses/LICENSE
stonerplots-1.9.0.dist-info/METADATA
stonerplots-1.9.0.dist-info/WHEEL
stonerplots-1.9.0.dist-info/top_level.txt
stonerplots-1.9.0.dist-info/RECORD
