Metadata-Version: 2.4
Name: StonerPlots
Version: 1.9.0
Summary: This is a fork of scienceplots and provides a range of matplotlib styles for plotting physics...
Author-email: Gavin Burnell <G.Burnell@leeds.ac.uk>
Project-URL: Homepage, https://github.com/stonerlab/stonerplots/
Project-URL: Issues, https://github.com/stonerlab/stonerplots/issues
Keywords: matplotlib-style-sheets,matplotlib-figures,scientific-papers,thesis-template,matplotlib-styles,python
Classifier: Programming Language :: Python :: 3
Classifier: License :: OSI Approved :: MIT License
Classifier: Operating System :: OS Independent
Requires-Python: >=3.10
License-File: LICENSE
Dynamic: license-file
